btc/__init__.py
btc/bitcoin.py
btc/chain.py
btc/encoding.py
btc/providers.py
btc/raw_transaction.py
btc/rpc_abi.py
btc/types_btc.py
btc/types_check.py
btc/utils.py
btc/wallet.py
btc_cj-1.0.3.dist-info/LICENSE
btc_cj-1.0.3.dist-info/METADATA
btc_cj-1.0.3.dist-info/WHEEL
btc_cj-1.0.3.dist-info/top_level.txt
btc_cj-1.0.3.dist-info/RECORD
