Metadata-Version: 2.1
Name: btc-cj
Version: 1.0.3
Summary: A package interact with bitcoin node
Home-page: https://github.com/wenqinchao/btc
Author: Wen
Author-email: wenqinchao@gmail.com
License: MIT
Platform: UNKNOWN
Classifier: Programming Language :: Python :: 3
Classifier: License :: OSI Approved :: MIT License
Classifier: Operating System :: OS Independent
Requires-Python: >=3.6
License-File: LICENSE
